{
  "level": {"levelNumber": 34, "title": "Database Management Basics", "description": "Introduction to database systems on Linux", "difficulty": "expert", "estimatedTimeMinutes": 40, "pointsReward": 170},
  "exercises": [
    {"exerciseNumber": 1, "title": "Start PostgreSQL Service", "description": "Use 'systemctl' to start PostgreSQL database server.", "initialSetup": {"directory": "/home/student"}, "validationRules": {"expectedBehavior": "starts_postgres"}, "hints": ["sudo systemctl start postgresql", "Starts PostgreSQL service", "Check status: systemctl status postgresql"], "solution": "sudo systemctl start postgresql", "points": 20, "difficultyStars": 2},
    {"exerciseNumber": 2, "title": "Connect to PostgreSQL", "description": "Use 'psql' to connect to PostgreSQL database.", "initialSetup": {"directory": "/home/student"}, "validationRules": {"expectedBehavior": "connects_psql"}, "hints": ["psql -U postgres -d template1", "U=user, d=database", "Or: sudo -u postgres psql"], "solution": "sudo -u postgres psql", "points": 20, "difficultyStars": 2},
    {"exerciseNumber": 3, "title": "List Databases", "description": "Use 'psql' command '\\l' to list databases.", "initialSetup": {"directory": "/home/student"}, "validationRules": {"expectedBehavior": "lists_databases"}, "hints": ["In psql prompt: \\l", "Lists all databases", "Also: SELECT datname FROM pg_database;"], "solution": "\\l", "points": 15, "difficultyStars": 2},
    {"exerciseNumber": 4, "title": "Create Database", "description": "Use 'createdb' to create new database.", "initialSetup": {"directory": "/home/student"}, "validationRules": {"expectedBehavior": "creates_db"}, "hints": ["sudo -u postgres createdb myapp", "Or: CREATE DATABASE myapp;", "From psql prompt"], "solution": "sudo -u postgres createdb myapp", "points": 20, "difficultyStars": 2},
    {"exerciseNumber": 5, "title": "Backup Database", "description": "Use 'pg_dump' to backup a PostgreSQL database.", "initialSetup": {"directory": "/home/student"}, "validationRules": {"expectedBehavior": "backups_db"}, "hints": ["pg_dump -U postgres db > backup.sql", "Exports database to SQL file", "Can restore: psql < backup.sql"], "solution": "pg_dump -U postgres db > backup.sql", "points": 25, "difficultyStars": 3}
  ]
}
